zenaura/__init__.py
zenaura/cli/__init__.py
zenaura/cli/cli.py
zenaura/cli/favicon.ico
zenaura/cli/files.py
zenaura/cli/logo.png
zenaura/client/__init__.py
zenaura/client/app.py
zenaura/client/component.py
zenaura/client/config.py
zenaura/client/dispatcher.py
zenaura/client/layout.py
zenaura/client/mutator.py
zenaura/client/page.py
zenaura/client/persistance.py
zenaura/client/algorithm/__init__.py
zenaura/client/algorithm/algorithm.py
zenaura/client/algorithm/operations.py
zenaura/client/algorithm/searcher.py
zenaura/client/algorithm/updater.py
zenaura/client/compiler/__init__.py
zenaura/client/compiler/attribute.py
zenaura/client/compiler/compiler.py
zenaura/client/compiler/sanitize.py
zenaura/client/dom/__init__.py
zenaura/client/dom/dom.py
zenaura/client/dom/error.py
zenaura/client/dom/mount.py
zenaura/client/dom/render.py
zenaura/client/dom/lifecycles/__init__.py
zenaura/client/dom/lifecycles/mount.py
zenaura/client/dom/lifecycles/render.py
zenaura/client/hydrator/__init__.py
zenaura/client/hydrator/compiler_adapter.py
zenaura/client/hydrator/hydrator.py
zenaura/client/hydrator/lookup.py
zenaura/client/hydrator/real_dom_adapter.py
zenaura/client/hydrator/tasker.py
zenaura/client/hydrator/virtual_dom_adapter.py
zenaura/client/observer/__init__.py
zenaura/client/observer/observer.py
zenaura/client/observer/subject.py
zenaura/client/tags/__init__.py
zenaura/client/tags/attribute.py
zenaura/client/tags/builder.py
zenaura/client/tags/html.py
zenaura/client/tags/node.py
zenaura/mocks/browser_mocks.py
zenaura/server/__init__.py
zenaura/server/server.py
zenaura/ui/__init__.py
zenaura/ui/alert.py
zenaura/ui/badge.py
zenaura/ui/breadcrumbs.py
zenaura/ui/button.py
zenaura/ui/card.py
zenaura/ui/charts.py
zenaura/ui/common.py
zenaura/ui/dropdown.py
zenaura/ui/flex.py
zenaura/ui/float_button.py
zenaura/ui/form.py
zenaura/ui/grid.py
zenaura/ui/icon.py
zenaura/ui/input.py
zenaura/ui/layout.py
zenaura/ui/menu.py
zenaura/ui/message.py
zenaura/ui/modal.py
zenaura/ui/pagination.py
zenaura-0.15.46.dist-info/LICENSE
zenaura-0.15.46.dist-info/METADATA
zenaura-0.15.46.dist-info/WHEEL
zenaura-0.15.46.dist-info/entry_points.txt
zenaura-0.15.46.dist-info/top_level.txt
zenaura-0.15.46.dist-info/RECORD
