Metadata-Version: 2.2
Name: zenaura
Version: 0.15.46
Summary: Zenaura is an experimental Python library built upon PyScript, designed to empower Python developers to create stateful, component-based Single Page Applications (SPAs). By leveraging a virtual DOM implementation, Zenaura optimizes the performance, reactivity, responsiveness, and interactivity of web applications. This allows developers to build high-performance, dynamic web applications using familiar Python concepts and syntax.
Author: Ahmed Rakan
Author-email: ar.aldhafeeri11@gmail.com
License-File: LICENSE
Requires-Dist: bleach==6.1.0
Dynamic: author
Dynamic: author-email
Dynamic: description
Dynamic: description-content-type
Dynamic: requires-dist
Dynamic: summary
